{
  "project_info": {
    "project_number": "778139492916",
    "firebase_url": "https://todoapp-4ec79.firebaseio.com",
    "project_id": "todoapp-4ec79",
    "storage_bucket": "todoapp-4ec79.appspot.com"
  },
  "client": [
    {
      "client_info": {
        "mobilesdk_app_id": "1:778139492916:android:ec9bcf221e8fc74a8ba061",
        "android_client_info": {
          "package_name": "com.firebase"
        }
      },
      "oauth_client": [
        {
          "client_id": "778139492916-eehim2tkoeqddpq39rb8j8c2v0q7uhh4.apps.googleusercontent.com",
          "client_type": 3
        }
      ],
      "api_key": [
        {
          "current_key": "AIzaSyCgiEdn7-sfQ-45gqxnphSS6NCC3dxEdSY"
        }
      ],
      "services": {
        "appinvite_service": {
          "other_platform_oauth_client": [
            {
              "client_id": "778139492916-eehim2tkoeqddpq39rb8j8c2v0q7uhh4.apps.googleusercontent.com",
              "client_type": 3
            }
          ]
        }
      }
    }
  ],
  "configuration_version": "1"
}